{
  "GoodSpec": {
    "Id": "Beavertail",
    "BackwardCompatibleIds": [],
    "DisplayNameLocKey": "Good.Beavertail.DisplayName",
    "PluralDisplayNameLocKey": "Good.Beavertail.PluralDisplayName",
    "ConsumptionEffects": [
      {
        "NeedId": "Hunger",
        "Points": 0.3
      },
      {
        "NeedId": "Beavertail",
        "Points": 0.2
      }
    ],
    "GoodType": "Box",
    "StockpileVisualization": "Box",
    "VisibleContainer": {
      "Value": "Box"
    },
    "ContainerColor": "#d16b57",
    "CarryingAnimation": "CarryInHands",
    "Weight": 1,
    "GoodGroupId": "Food",
    "Icon": "Sprites/Goods/BeavertailIcon",
    "RequiredFeatureToggle": ""
  }
}